[{
        "p_id": 101,
        "p_category": "Kitchen_Appliances",
        "p_name": "2 SLICE SANDWICH MAKER Grill  (Black & Steel)",
        "brand": "Nova",
        "price": 1695,
        "image": "https://rukminim1.flixcart.com/image/416/416/k0sgl8w0/sandwich-maker/c/e/4/nova-2-slice-panni-grill-sandwich-maker-original-imafkgcmggv7me6p.jpeg?q=70"
    },
    {
        "p_id": 102,
        "p_category": "Kitchen_Appliances",
        "p_name": "Favourite IC 1800 W Induction Cooktop  (Black, Push Button)",
        "brand": "Pigeon",
        "price": 1399,
        "image": "https://rukminim1.flixcart.com/image/416/416/induction-cook-top/5/c/k/pigeon-favourite-ic-1800-w-favourite-ic-1800-w-original-imaenreqhefzd63h.jpeg?q=70"
    },
    {
        "p_id": 103,
        "p_category": "Home_Appliances",
        "p_name": "Ujala 1200 mm Energy Saving 3 Blade Ceiling Fan  (Brown, Pack of 1)",
        "brand": "Orient Electric",
        "price": 1399,
        "image": "https://rukminim1.flixcart.com/image/416/416/k0h12fk0/fan/9/z/t/ujala-ceiling-fan-1200-orient-electric-original-imafk9a2c4fghhwm.jpeg?q=70"
    },
    {
        "p_id": 104,
        "p_category": "Kitchen_Appliances",
        "p_name": "HL1655/00 250 W Hand Blender  (White)",
        "brand": "Philips",
        "price": 1550,
        "image": "https://images-na.ssl-images-amazon.com/images/I/41-5nd-r6bL._SX425_.jpg"
    },
    {
        "p_id": 105,
        "p_category": "Kitchen_Appliances",
        "p_name": "Rapid 4 Jar 750 watts 750 W Juicer Mixer Grinder  (Black, 4 Jars)",
        "brand": "Butterfly",
        "price": 2799,
        "image": "https://rukminim1.flixcart.com/image/416/416/jmi22kw0/mixer-grinder-juicer/n/z/a/butterfly-rapid-4-jar-750-watts-original-imaf5dvgugcqyug3.jpeg?q=70"
    },
    {
        "p_id": 106,
        "p_category": "Kitchen_Appliances",
        "p_name": "HR7627/00 650 W Food Processor  (White)",
        "brand": "Philips",
        "price": 4250,
        "image": "https://rukminim1.flixcart.com/image/416/416/food-processor/p/b/h/daily-collection-philips-hr7627-original-imaedkswqnfjmhu5.jpeg?q=70"
    },
    {
        "p_id": 107,
        "p_category": "Water_Purifiers",
        "p_name": "Ace Plus 8 L RO + UV + UF + TDS Water Purifier  (White)",
        "brand": "Kent",
        "price": 12999,
        "image": "https://rukminim1.flixcart.com/image/416/416/jxjahe80/water-purifier/y/g/7/kent-ace-plus-original-imafhzawerdykpeh.jpeg?q=70"
    },
    {
        "p_id": 108,
        "p_category": "Water_Purifiers",
        "p_name": "LIV-PEP-PRO-PLUS+ 7 L RO + UV + UF Water Purifier  (White)",
        "brand": "Livpure",
        "price": 9299,
        "image": "https://rukminim1.flixcart.com/image/416/416/j13vqfk0/water-purifier/8/n/7/livpure-pep-pro-original-imaesrgs2c2gtyvh.jpeg?q=70"
    },
    {
        "p_id": 109,
        "p_category": "Home_Appliances",
        "p_name": "Oeh-1220 OEH-1220 Fan Room Heater",
        "brand": "Orpat",
        "price": 1079,
        "image": "https://rukminim1.flixcart.com/image/416/416/jpsnma80/room-heater/x/d/b/oeh-1220-orpat-original-imafbyqfvmzaqrxf.jpeg?q=70"
    },
    {
        "p_id": 110,
        "p_category": "Window_Air_Conditioners",
        "p_name": "1.5 Ton 3 Star Window AC - White  (183 DZA (R32), Copper Condenser)",
        "brand": "Voltas",
        "price": 23999,
        "image": "https://rukminim1.flixcart.com/image/416/416/jy3anbk0/air-conditioner-new/z/b/y/183-dza-r32-1-5-window-fixed-speed-voltas-original-imafgbz9hpnkwhs4.jpeg?q=70"
    },
    {
        "p_id": 111,
        "p_category": "Air_Conditioners",
        "p_name": "1.5 Ton 3 Star Split Inverter AC with PM 2.5 Filter - White  (18K 3 Star Ester Neo Inverter, Copper Condenser)",
        "brand": "Carrier",
        "price": 30499,
        "image": "https://rukminim1.flixcart.com/image/416/416/jtyouq80/air-conditioner-new/s/f/8/18k-3-star-ester-neo-inverter-r32-idu-i011-18k-3star-inverter-original-imaff727rpzg3nhz.jpeg?q=70"
    },
    {
        "p_id": 112,
        "p_category": "Air_Conditioners",
        "p_name": "1.2 Ton 5 Star Split Inverter AC - White  (155V DZW (R32), Copper Condenser)",
        "brand": "Voltas",
        "price": 31499,
        "image": "https://rukminim1.flixcart.com/image/416/416/jucz98w0/air-conditioner-new/z/h/q/155v-dzw-r32-1-2-split-voltas-inverter-original-imaffdt8gyxqxfae.jpeg?q=70"
    },
    {
        "p_id": 113,
        "p_category": "Wrist_Watch",
        "p_name": "G736 Analog Digital Watch - For Men",
        "brand": "G Shock",
        "price": 16145,
        "image": "https://rukminim1.flixcart.com/image/800/960/jmxrwy80/watch/e/e/w/g736-casio-original-imaeykdxegwfrcgv.jpeg?q=50"
    },

    {
        "p_id": 114,
        "p_category": "Television",
        "p_name": "163cm (65 inch) Ultra HD (4K) LED Smart TV ",
        "brand": "Samsung",
        "price": 129999,
        "image": "https://rukminim1.flixcart.com/image/352/352/k1xwcy80/television/v/p/m/samsung-ua65ru8000kxxl-original-imafhc5jhmgwbepj.jpeg?q=70"
    },

    {
        "p_id": 115,
        "p_category": "Kitchen_Appliance",
        "p_name": "Rapid Electric Kettle (1.5 L, Black) & Eco750 ml water bottle",
        "brand": "Butterfly",
        "price": 699,
        "image": "https://rukminim1.flixcart.com/image/416/416/k0wqwsw0/electric-kettle/g/t/d/butterfly-rapid-kettle-1-5-litre-wave-750-ml-water-bottle-rapid-original-imafkfy7zaekbubs.jpeg?q=70"
    },

    {
        "p_id": 116,
        "p_category": "Furniture",
        "p_name": "Duster Leather 1 Seater Sofa  (Finish Color - Beige) ",
        "brand": "Couch Italia",
        "price": 37390,
        "image": "https://rukminim1.flixcart.com/image/416/416/jog2nbk0/sofa-sectional/g/y/z/beige-corrected-leather-ci-dt-bl-1s-couch-italia-beige-original-imafawjhwc6fwqem.jpeg?q=70"
    },

    {
        "p_id": 117,
        "p_category": "Hair_Dresser",
        "p_name": "Freshers pack NHS 870 + NHP 8100/05 Personal Care Appliance Combo  (Hair Straightener, Hair Dryer)",
        "brand": "Nova",
        "price": 999,
        "image": "https://rukminim1.flixcart.com/image/416/416/jz1l7rk0/personal-care-app-combo/z/t/s/freshers-pack-nhs-870-nhp-8100-05-nova-original-imafj5a2tyf8nxnf.jpeg?q=70"
    },

    {
        "p_id": 118,
        "p_category": "Headsets",
        "p_name": "Rockerz 255F Bluetooth Headset  (Active Black, Wireless in the ear)",
        "brand": "Boat",
        "price": 1499,
        "image": "https://rukminim1.flixcart.com/image/416/416/ka5oia80/headphone/a/h/7/rockerz-255f-rockerz-255-boat-original-imafrhehhzrkd6hv.jpeg?q=70"
    },

    {
        "p_id": 119,
        "p_category": "Mobiles",
        "p_name": "Note 7 Pro (Space Black, 64 GB)  (6 GB RAM)",
        "brand": "Redmi",
        "price": 12999,
        "image": "https://rukminim1.flixcart.com/image/416/416/k0lbdzk0pkrrdj/mobile/z/j/a/mi-redmi-note-7-pro-mzb7465in-original-imafhvrdmeyweauc.jpeg?q=70"
    },

    {
        "p_id": 120,
        "p_category": "Sport_Shoes",
        "p_name": "ALEXA Running Shoes For Women  (Black)",
        "brand": "Campus",
        "price": 1444,
        "image": "https://rukminim1.flixcart.com/image/800/960/jwpa8i80/shoe/z/b/h/5g-663-9-campus-blk-rani-original-imafhcyyxzyz9dbx.jpeg?q=50"
    }
]